{
	"selector": ":root",
	"update_comment": "",
	"ownerId": "",
	"persistence": "none",
	"settings": {
		"postrequestbody": "",
		"authentication": "none",
		"auth_password": "",
		"typerequest": "HTTP_GET",
		"urlrandom": "0",
		"auth_userid": "",
		"url": "http://10.0.10.15:8080/dsn-server-0.1-SNAPSHOT/api/v0/customers/{id}",
		"dbdriver": "",
		"dbnames": {
			"database": "",
			"collection": ""
		}
	},
	"appexpr": [],
	"format": "json",
	"dependency": "",
	"category": "567",
	"description": "",
	"name": "qGetCustomer",
	"connector": "http",
	"requestDate": "2015-03-30T07:55:09.815Z",
	"parameters": [
		{
			"name": "id",
			"type": "url",
			"value": "987654321",
			"operation": "eq"
		}
	],
	"metadata": "{\"name\":\"root\",\"type\":\"root\",\"children\":{\"id\":{\"name\":\"id\",\"type\":\"String\",\"options\":{\"properties\":{},\"gcontrols\":[{\"name\":\"SimpleText\",\"perspective\":\"Default\",\"type\":\"TextField\",\"attributes\":{\"label\":\"id\"},\"styles\":{}},{\"name\":\"SimpleEdit\",\"perspective\":\"Edit\",\"type\":\"TextField\",\"attributes\":{\"label\":\"id\"},\"styles\":{}}]},\"children\":{}},\"name\":{\"name\":\"name\",\"type\":\"String\",\"options\":{\"properties\":{},\"gcontrols\":[{\"name\":\"SimpleText\",\"perspective\":\"Default\",\"type\":\"TextField\",\"attributes\":{\"label\":\"name\"},\"styles\":{}},{\"name\":\"SimpleEdit\",\"perspective\":\"Edit\",\"type\":\"TextField\",\"attributes\":{\"label\":\"name\"},\"styles\":{}}]},\"children\":{}},\"created\":{\"name\":\"created\",\"type\":\"String\",\"options\":{\"properties\":{},\"gcontrols\":[{\"name\":\"SimpleText\",\"perspective\":\"Default\",\"type\":\"TextField\",\"attributes\":{\"label\":\"created\"},\"styles\":{}},{\"name\":\"SimpleEdit\",\"perspective\":\"Edit\",\"type\":\"TextField\",\"attributes\":{\"label\":\"created\"},\"styles\":{}}]},\"children\":{}}}}",
	"source": "ext",
	"visibility": "visible",
	"lock": {
		"status": "unlocked"
	},
	"precode": [],
	"postcode": [],
	"service": {
		"name": "",
		"method": ""
	},
	"_id": "5519015df93945e4199d9f78",
	"versioning": {
		"DhatimDsn": {
			"last_action": "1427713165",
			"status": "committed",
			"user": "admin"
		}
	}
}